odoo10_addon_stock_delivery_internal-10.0.1.0.0-py2.7-nspkg.pth
odoo/addons/stock_delivery_internal/README.rst
odoo/addons/stock_delivery_internal/__init__.py
odoo/addons/stock_delivery_internal/__manifest__.py
odoo/addons/stock_delivery_internal/data/stock_pickup_request.xml
odoo/addons/stock_delivery_internal/models/__init__.py
odoo/addons/stock_delivery_internal/models/delivery_carrier.py
odoo/addons/stock_delivery_internal/models/stock_picking.py
odoo/addons/stock_delivery_internal/models/stock_pickup_request.py
odoo/addons/stock_delivery_internal/security/ir.model.access.csv
odoo/addons/stock_delivery_internal/static/description/icon.png
odoo/addons/stock_delivery_internal/tests/__init__.py
odoo/addons/stock_delivery_internal/tests/common.py
odoo/addons/stock_delivery_internal/tests/test_stock_picking.py
odoo/addons/stock_delivery_internal/tests/test_stock_pickup_request.py
odoo/addons/stock_delivery_internal/views/delivery_carrier_view.xml
odoo/addons/stock_delivery_internal/views/stock_pickup_request_view.xml
odoo10_addon_stock_delivery_internal-10.0.1.0.0.dist-info/DESCRIPTION.rst
odoo10_addon_stock_delivery_internal-10.0.1.0.0.dist-info/METADATA
odoo10_addon_stock_delivery_internal-10.0.1.0.0.dist-info/RECORD
odoo10_addon_stock_delivery_internal-10.0.1.0.0.dist-info/WHEEL
odoo10_addon_stock_delivery_internal-10.0.1.0.0.dist-info/metadata.json
odoo10_addon_stock_delivery_internal-10.0.1.0.0.dist-info/namespace_packages.txt
odoo10_addon_stock_delivery_internal-10.0.1.0.0.dist-info/top_level.txt
